py_fpl_api-0.0.7.dist-info/DESCRIPTION.rst
py_fpl_api-0.0.7.dist-info/METADATA
py_fpl_api-0.0.7.dist-info/RECORD
py_fpl_api-0.0.7.dist-info/WHEEL
py_fpl_api-0.0.7.dist-info/metadata.json
py_fpl_api-0.0.7.dist-info/top_level.txt
py_fpl_api-0.0.7.dist-info/zip-safe
pyfplapi/__init__.py
